polynomial_equations-0.1.0.dist-info/licenses/LICENSE
polynomials/__init__.py
polynomials/version.py
polynomials/base/__init__.py
polynomials/base/calculus.py
polynomials/base/formatting.py
polynomials/base/polynomial.py
polynomials/base/roots.py
polynomials/base/validation.py
polynomials/cubic/__init__.py
polynomials/cubic/accelerated.py
polynomials/cubic/numeric.py
polynomials/cubic/properties.py
polynomials/cubic/symbolic.py
polynomials/plotting/__init__.py
polynomials/plotting/animation.py
polynomials/plotting/static.py
polynomials/quadratic/__init__.py
polynomials/quadratic/accelerated.py
polynomials/quadratic/numeric.py
polynomials/quadratic/properties.py
polynomials/quadratic/symbolic.py
polynomials/utils/__init__.py
polynomials/utils/numeric.py
polynomials/utils/symbolic.py
polynomials/utils/types.py
polynomials/web/__init__.py
polynomials/web/streamlit_app.py
polynomial_equations-0.1.0.dist-info/METADATA
polynomial_equations-0.1.0.dist-info/WHEEL
polynomial_equations-0.1.0.dist-info/top_level.txt
polynomial_equations-0.1.0.dist-info/RECORD
