Metadata-Version: 2.4
Name: polynomial-equations
Version: 0.1.0
Summary: Numeric, symbolic, and accelerated quadratic and cubic equations library
Author-email: Arsalan Jafarnezhad <arsalan.jafarnezhad.2010@gmail.com>
License: MIT
Requires-Python: >=3.10
License-File: LICENSE
Requires-Dist: numpy>=1.24
Requires-Dist: matplotlib>=3.7
Requires-Dist: sympy>=1.12
Requires-Dist: numba>=0.57
Requires-Dist: streamlit>=1.27
Dynamic: license-file
